{
  "tickets_for_sale": [
    {
      "updated": "2022-09-15 20:30:12.934342",
      "id": "TGlzdGluZzo3NjE2NzMy",
      "description": "kaartje voor Frenna ivm ziekte ",
      "event_name": "Frenna Freak In The Weekend",
      "event_start_date": "2022-09-16T22:00:00+02:00",
      "event_end_date": null,
      "amount_of_tickets": 1,
      "entrance_slug": "regular-tickets",
      "entrance_id": "RXZlbnRUeXBlOjIzNzI1OTE=",
      "original_price": 26.0,
      "price": 28.12,
      "location": "Club Merlijn",
      "city": "Hengelo",
      "url": "http://ticketswap.com/listing/frenna-freak-in-the-weekend/7616732/59599324c1?utm_campaign=publishedListingShare&utm_source=ticketswap&utm_medium=manualshare"
    }
  ],
  "tickets_sold": [
    {
      "updated": "2022-09-15 20:30:13.102452",
      "id": "TGlzdGluZzo3NjE2NzMy",
      "description": "kaartje voor Frenna ivm ziekte ",
      "event_name": "Frenna Freak In The Weekend",
      "event_start_date": "2022-09-16T22:00:00+02:00",
      "event_end_date": null,
      "amount_of_tickets": 2,
      "entrance_title": "Regular",
      "entrance_id": "RXZlbnRUeXBlOjIzNzI1OTE=",
      "original_price": 26.0,
      "price": 28.12,
      "location": "Club Merlijn",
      "city": "Hengelo",
      "url": "http://ticketswap.com/listing/frenna-freak-in-the-weekend/7616732/59599324c1?utm_campaign=publishedListingShare&utm_source=ticketswap&utm_medium=manualshare"
    }
  ],
  "events": [
    {
      "id": "RXZlbnQ6OWIxMzg1MzktMjc3NC00OTgxLTkyM2MtMWMxZjhiNWUwNjA2",
      "entrance_slug": "frenna-freak-in-the-weekend",
      "name": "Frenna Freak In The Weekend",
      "start_date": "2022-09-16T22:00:00+02:00",
      "end_date": null,
      "location": "Club Merlijn",
      "city": "Hengelo",
      "available_tickets": "1",
      "sold_tickets": "18",
      "wanted_tickets": "26",
      "entrance_types": [
        {
          "id": "RXZlbnRUeXBlOjIzNzI1OTE=",
          "slug": "regular-tickets",
          "title": "Regular",
          "start_date": "2022-09-16T22:00:00+02:00",
          "end_date": null,
          "available_tickets": 1
        }
      ]
    }
  ]
}
